iota_client-1.0.0rc2.dist-info/METADATA
iota_client-1.0.0rc2.dist-info/WHEEL
iota_client/_base_api.py
iota_client/client.py
iota_client/__init__.py
iota_client/secret_manager.py
iota_client/common.py
iota_client/_high_level_api.py
iota_client/_node_core_api.py
iota_client/_utils.py
iota_client/_node_indexer_api.py
iota_client/iota_client.cpython-39-darwin.so
iota_client-1.0.0rc2.dist-info/RECORD
