Metadata-Version: 2.1
Name: iota-client
Version: 1.0.0rc2
Summary: Python bindings for the IOTA client library
Keywords: iota,tangle,client,python
Home-Page: https://www.iota.org/
Author: IOTA Stiftung
License: Apache-2.0
Project-URL: Source Code, https://github.com/iotaledger/iota.rs
